baidu-ai-tool/__init__.py
baidu_ai_tool/__init__.py
baidu_aitool/__init__.py
baidu_aitool-0.0.4.dist-info/LICENSE
baidu_aitool-0.0.4.dist-info/METADATA
baidu_aitool-0.0.4.dist-info/WHEEL
baidu_aitool-0.0.4.dist-info/top_level.txt
baidu_aitool-0.0.4.dist-info/RECORD
