Metadata-Version: 2.1
Name: baidu-aitool
Version: 0.0.4
Summary: 配合百度AI进行图像识别的工具
Home-page: https://github.com/yuanyunqiang
Author: 袁运强
Author-email: 6497569033@qq.com
License: UNKNOWN
Platform: UNKNOWN
Classifier: Programming Language :: Python :: 3
Classifier: License :: OSI Approved :: MIT License
Classifier: Operating System :: OS Independent
Requires-Python: >=3.6
License-File: LICENSE
